LICENSE
pymetaheuristics/__init__.py
pymetaheuristics/genetic_algorithm/__init__.py
pymetaheuristics/genetic_algorithm/exceptions.py
pymetaheuristics/genetic_algorithm/model.py
pymetaheuristics/genetic_algorithm/steps/__init__.py
pymetaheuristics/genetic_algorithm/steps/crossovers.py
pymetaheuristics/genetic_algorithm/steps/multations.py
pymetaheuristics/genetic_algorithm/steps/selections.py
pymetaheuristics/genetic_algorithm/types.py
pymetaheuristics/utils/distances.py
pymetaheuristics-0.1.1.dist-info/LICENSE
pymetaheuristics-0.1.1.dist-info/WHEEL
pymetaheuristics-0.1.1.dist-info/METADATA
pymetaheuristics-0.1.1.dist-info/RECORD
