Metadata-Version: 2.1
Name: pymetaheuristics
Version: 0.1.1
Summary: 
Home-page: https://github.com/igormcsouza/pymetaheuristics
License: MIT
Keywords: metaheuristics,python,solver
Author: Igor Souza
Author-email: igormcsouza@gmail.com
Requires-Python: >=3.7,<4.0
Classifier: License :: OSI Approved :: MIT License
Classifier: Programming Language :: Python :: 3
Classifier: Programming Language :: Python :: 3.7
Classifier: Programming Language :: Python :: 3.8
Classifier: Programming Language :: Python :: 3.9
Project-URL: Repository, https://github.com/igormcsouza/pymetaheuristics
